{
  "script_id": "317",
  "name": "vera.vim",
  "summary": "Syntax file for the Vera language",
  "script_type": "syntax",
  "description": "This is a vera.vim syntax file.  It\nhas been updated to reflect Vera 5.0.\nDeprecated tasks in the language are\nnow linked to \"Error\" in order to\nhighlight them in the code.",
  "rating_total": "28",
  "rating_votes": "18",
  "downloads": "517",
  "install_details": ":so vera.vim",
  "versions": [
    {
      "url": "http://www.vim.org/scripts/download_script.php?src_id=924",
      "filename": "vera.vim",
      "script_version": "1.0",
      "date": "2002-06-14",
      "vim_version": "6.0",
      "author": {
        "user_id": "710",
        "user_name": "Beth",
        "first_name": "Beth",
        "last_name": "Leonard",
        "email": "beth at slimy.com",
        "homepage": "http://www.slimy.com/~beth"
      },
      "release_notes": "Initial upload"
    }
  ]
}
