{
  "script_id": "979",
  "name": "idf.vim",
  "summary": "Syntax highlighting for EnergyPlus IDF files.",
  "script_type": "syntax",
  "description": "Idf.vim provides basic syntax support for EnergyPlus IDF files.",
  "rating_total": "5",
  "rating_votes": "2",
  "downloads": "189",
  "install_details": "Drop it in a \"syntax\" directory.",
  "versions": [
    {
      "url": "http://www.vim.org/scripts/download_script.php?src_id=2998",
      "filename": "idf.vim",
      "script_version": "0.1",
      "date": "2004-05-06",
      "vim_version": "6.0",
      "author": {
        "user_id": "5118",
        "user_name": "cschiefer",
        "first_name": "Christian",
        "last_name": "Schiefer",
        "email": "christian.schiefer at chello.at",
        "homepage": ""
      },
      "release_notes": "Initial upload"
    }
  ]
}