{
  "script_id": "1016",
  "display_name": "corewars.vim",
  "summary": "syntax definitions for corewars cw-assembler",
  "name": "corewars.vim",
  "script_type": "syntax",
  "description": "This file provides syntax definitions of the corewars cw-assembly language.",
  "rating_total": "1",
  "rating_votes": "1",
  "downloads": "210",
  "install_details": "Put corewars.vim in ~/.vim/syntax .\nYou may want to add a line to ~/.vimrc or ~/.vim/filetype.vim to autodetect *.cw files.",
  "versions": [
    {
      "url": "http://www.vim.org/scripts/download_script.php?src_id=3160",
      "filename": "corewars.vim",
      "script_version": "1.2",
      "date": "2004-06-19",
      "vim_version": "6.0",
      "author": {
        "user_id": "5421",
        "user_name": "lorenzwegener",
        "first_name": "Lorenz",
        "last_name": "Wegener",
        "email": "lorenzwegener at hotmail.com",
        "homepage": ""
      },
      "release_notes": "Initial upload"
    }
  ]
}
