{
  "script_id": "1089",
  "display_name": "sas.vim",
  "summary": "SAS indent file",
  "name": "sas.vim",
  "script_type": "indent",
  "description": "SAS indent file.",
  "rating_total": "4",
  "rating_votes": "1",
  "downloads": "366",
  "install_details": "Unix or Linux: copy the script into $HOME/.vim/indent or in $VIM/vimfiles\nWindows: copy the script into $VIM_INSTALL_DIR\\vimfiles\\indent",
  "versions": [
    {
      "url": "http://www.vim.org/scripts/download_script.php?src_id=4193",
      "filename": "sas.vim",
      "script_version": "0.3",
      "date": "2005-04-22",
      "vim_version": "6.0",
      "author": {
        "user_id": "5996",
        "user_name": "largezoo",
        "first_name": "Jianzhong",
        "last_name": "Liu",
        "email": "jliu7 at uiuc.edu",
        "homepage": ""
      },
      "release_notes": "1. correct a bug of comments \n2. correct a bug of statement %IF ... %THEN %DO; \n3. TODO: fault tolerance (missing RUN) within a macro"
    },
    {
      "url": "http://www.vim.org/scripts/download_script.php?src_id=3488",
      "filename": "sas.vim",
      "script_version": "0.2",
      "date": "2004-09-25",
      "vim_version": "6.0",
      "author": {
        "user_id": "5996",
        "user_name": "largezoo",
        "first_name": "Jianzhong",
        "last_name": "Liu",
        "email": "jliu7 at uiuc.edu",
        "homepage": ""
      },
      "release_notes": "1. Fixed a bug for if statement\n2. More flexibility for statements with do\n3. Add fault tolerance for missing \"run;\" statements at the end of data/proc step"
    }
  ]
}
