{
  "script_id": "1867",
  "name": "doctest syntax",
  "summary": "Highlighting for Python doctest files",
  "script_type": "syntax",
  "description": "Syntax file for highlighting Python doctest files. This is usefull for when you have your doctests in a seperate from your source code (in a .txt file). The syntax highlighter will color the ReST headers, code blocks and expected values.",
  "rating_total": "15",
  "rating_votes": "6",
  "downloads": "407",
  "install_details": "Place the vim file into a syntax dir and set the filetype to doctest.",
  "versions": [
    {
      "url": "http://www.vim.org/scripts/download_script.php?src_id=7002",
      "filename": "doctest.vim",
      "script_version": "0.1",
      "date": "2007-04-19",
      "vim_version": "7.0",
      "author": {
        "user_id": "12246",
        "user_name": "jvloothuis",
        "first_name": "Jeroen",
        "last_name": "Vloothuis",
        "email": "jeroen.vloothuis at xs4all.nl",
        "homepage": ""
      },
      "release_notes": "Initial upload"
    }
  ]
}
