{
  "script_id": "1973",
  "name": "JET_toggle",
  "summary": "Dynamically add sets of commands to toggle between with a hotkey",
  "script_type": "utility",
  "description": "<!-- === START_DOC\n*JET_toggle.txt*           Plugin to dynamically add toggles #version#\n\n\n                         JET_TOGGLE REFERENCE MANUAL~\n\n\n\n\n\n==============================================================================\nCONTENTS {{{2                                        *JET_togglelist-contents* \n\n    1. Intro ................................... |JET_toggle|\n    2. How to add a toggle ..................... |JET_toggle-howto|\n    3. Feedback ................................ |JET_toggle-feedback|\n\n==============================================================================\n1. Intro {{{2                                                     *JET_toggle*\n\n    JET_toggle provides a mechanism for adding toggle commands and mapping\n  them to a shortcut.\n\n==============================================================================\n2. How to add a toggle {{{2                                 *JET_toggle-howto*\n\n  Source the script from your .vimrc, and then add whatever toggles you want.\n  \n\n  Syntax:\n  \n    JET_AddToggle(':someCommandString', ':someOtherCommandString', '<keymap>')\n  \n  \n  Example:\n  \n    source ~/.vim/plugin/JET_toggle.vim\n    JET_AddToggle(':set list', ':set nolist', '<C-l>')\n    JET_AddToggle(':set paste', ':set nopaste', '<M-p>')\n  \n\n    Then, when you type control-l it will toggle between ':set list' and\n  ':set nolist' and when you type alt-p it will toggle between ':set paste'\n  and ':set nopaste'.\n  \n==============================================================================\n3. Feedback {{{2                                         *JET_toggle-feedback*\n\n  Constructive feedback is welcome, send it to outtatime.at-symbol.gmail.com\n  with [JET_toggle] in the subject line.  Enjoy!\n-->",
  "rating_total": "17",
  "rating_votes": "8",
  "downloads": "146",
  "install_details": "Source it from your .vimrc file and it will do the rest.",
  "versions": [
    {
      "url": "http://www.vim.org/scripts/download_script.php?src_id=7425",
      "filename": "JET_toggle.vim",
      "script_version": "0.1",
      "date": "2007-07-28",
      "vim_version": "7.0",
      "author": {
        "user_id": "11852",
        "user_name": "Vimpire",
        "first_name": "Jai",
        "last_name": "Tkker",
        "email": "-",
        "homepage": "http://bf2e.com/"
      },
      "release_notes": "Initial upload"
    }
  ]
}
