{
  "script_id": "2029",
  "display_name": "4NT Bundle",
  "summary": "btm (Batch to Memory - 4NT, TakeCommand Script) filetype bundle",
  "name": "4NT-Bundle",
  "script_type": "ftplugin",
  "description": "Updates both the file type and syntax plug-in for btm (Batch to Memory - 4NT, TakeCommand Script) file type Bundle. Includes simple user and omni completion.\n\nReports errors to: http://code.google.com/p/vim-scripts/issues/list\nDiscuss improvements on: http://groups.google.com/group/vim_scripts\n\nhttp://code.google.com/p/vim-scripts/wiki/4NTBundle",
  "rating_total": "20",
  "rating_votes": "5",
  "downloads": "279",
  "install_details": "Just install using vimball (vimscript#1502). Check btm_options.vim for options used by this plug-in.",
  "versions": [
    {
      "url": "http://www.vim.org/scripts/download_script.php?src_id=7721",
      "filename": "btm-1.1.vba",
      "script_version": "1.1",
      "date": "2007-09-27",
      "vim_version": "7.0",
      "author": {
        "user_id": "7818",
        "user_name": "krischik",
        "first_name": "Martin",
        "last_name": "Krischik",
        "email": "krischik at users.sourceforge.net",
        "homepage": "http://ada.krischik.com/index.php/VIM/HomePage"
      },
      "release_notes": "Fixes and new features:\n\n1) Bill McCarthy contributed matchit settings.\n2) some loop-keywords where missing.\n3) additional minor fixes"
    },
    {
      "url": "http://www.vim.org/scripts/download_script.php?src_id=7718",
      "filename": "btm-1.0.vba",
      "script_version": "1.0",
      "date": "2007-09-26",
      "vim_version": "7.0",
      "author": {
        "user_id": "7818",
        "user_name": "krischik",
        "first_name": "Martin",
        "last_name": "Krischik",
        "email": "krischik at users.sourceforge.net",
        "homepage": "http://ada.krischik.com/index.php/VIM/HomePage"
      },
      "release_notes": "Initial upload"
    }
  ]
}
