{
  "script_id": "2051",
  "display_name": "enscript-highlight",
  "summary": "EnScript Syntax HighLighting",
  "name": "enscript-highlight",
  "script_type": "syntax",
  "description": "This plugin adds syntax highlighting for Encase Scripts (aka enscript files).\n\nActually it is a modified version of the cpp.vim module, but I'm planning to add autocompletion and more fixups.\n\nPlease. Feel free to send me patches and bug reports to: g??cnapnxr@lbhgrez.pbz",
  "install_details": "On w32:\n - Copy the vimfiles/ directory into your vim home.\n - Copy enscript.vim into your vim's home\n - Add this line to your vimrc: (_vimrc on w32):\n   source /path/to/vim/enscript.vim\n\nThere's a sample vimrc that you can get it if you want to test my vim configuration :)",
  "versions": [
    {
      "url": "http://www.vim.org/scripts/download_script.php?src_id=7825",
      "filename": "VimEnscript.rar",
      "script_version": "0.1",
      "date": "2007-10-24",
      "vim_version": "6.0",
      "author": {
        "user_id": "13281",
        "user_name": "pancake",
        "first_name": "( pancake",
        "last_name": ")",
        "email": "pancake at youterm.com",
        "homepage": ""
      },
      "release_notes": "Initial upload"
    }
  ]
}
