{
  "script_id": "2254",
  "display_name": "musicbox.vim",
  "summary": "musicbox allow you to play music files in vim",
  "name": "musicbox.vim",
  "script_type": "utility",
  "description": "musicbox is a vim plugin allowing to play mp3,ogg,wma... files in vim. It's a python plugin requiring gstreamer installed (alpha version, code GPL)",
  "rating_total": "3",
  "rating_votes": "10",
  "downloads": "508",
  "install_details": "copy musicbox.vim in your plugin directory\n(~/.vim/plugin)\n Then, to try the plugin, just do :\n launch vim\n :tabe playlist.txt\n :r !ls -d /home/user/music/album/*\n  then press c-h to play file under the cursor\n  c-j to pause\n  c-k to stop \n  c-n to play next file in list\n  c-p to play previous file in list\n",
  "versions": [
    {
      "url": "http://www.vim.org/scripts/download_script.php?src_id=8738",
      "filename": "musicbox.vim",
      "script_version": "1.0",
      "date": "2008-05-27",
      "vim_version": "7.0",
      "author": {
        "user_id": "14493",
        "user_name": "ga6ri3l",
        "first_name": "nicolas",
        "last_name": "bigeard",
        "email": "ga6ri3l at gmail.com",
        "homepage": "http://bigeard.nicolas.neuf.fr"
      },
      "release_notes": "Initial upload"
    }
  ]
}
