{
  "script_id": "2480",
  "name": "maroloccio",
  "summary": "An easy-on-the-eyes dark background colour scheme. ",
  "script_type": "color scheme",
  "description": "An easy-on-the-eyes dark background colour scheme.\n\nNow with 256 colours support!\n\nScreenshots:\n\nGUI mode: http://picasaweb.google.com/lh/photo/InGod978VFzY144k3-ZrxA\ncterm (256 colours): http://picasaweb.google.com/lh/photo/E5Nb1dltZxIoCtrFZ-OlnA\ncterm (8 colours): http://picasaweb.google.com/lh/photo/j_VMoZ20KLJaTq2YYeAdfg\n\nDownload from:\n\nVim.org: http://www.vim.org/scripts/script.php?script_id=2480\nGoogle Docs: http://docs.google.com/View?id=dd6g79bh_13f4gjx4nt\nEasy-to-remember URL: http://bit.ly/maroloccio_vim\n\nPlease send feeback to the author! maroloccio[at]gmail.com\n\n--\nPS: Eclipse user? Check out this as well:\n\nEclipse colour scheme: http://docs.google.com/View?id=dd6g79bh_15f2jhs9f8\nScreenshot: http://picasaweb.google.com/lh/photo/o7mWcx9G8TMXoU80S--_uw",
  "install_details": "Copy to colour scheme directory.",
  "versions": [
    {
      "url": "http://www.vim.org/scripts/download_script.php?src_id=12609",
      "filename": "maroloccio.vim",
      "script_version": "0.3.1",
      "date": "2010-03-12",
      "vim_version": "7.0",
      "author": {
        "user_id": "15725",
        "user_name": "maroloccio@yahoo.com",
        "first_name": "Marco",
        "last_name": "Ippolito",
        "email": "maroloccio at yahoo.com",
        "homepage": ""
      },
      "release_notes": "Updated licensing and author's contact details to receive feedback."
    },
    {
      "url": "http://www.vim.org/scripts/download_script.php?src_id=10543",
      "filename": "maroloccio.vim",
      "script_version": "0.3.0",
      "date": "2009-05-06",
      "vim_version": "7.0",
      "author": {
        "user_id": "15725",
        "user_name": "maroloccio@yahoo.com",
        "first_name": "Marco",
        "last_name": "Ippolito",
        "email": "maroloccio at yahoo.com",
        "homepage": ""
      },
      "release_notes": "Try it! Updated 256 colours terminal support!"
    },
    {
      "url": "http://www.vim.org/scripts/download_script.php?src_id=10334",
      "filename": "maroloccio.vim",
      "script_version": "0.2.9",
      "date": "2009-04-02",
      "vim_version": "7.0",
      "author": {
        "user_id": "15725",
        "user_name": "maroloccio@yahoo.com",
        "first_name": "Marco",
        "last_name": "Ippolito",
        "email": "maroloccio at yahoo.com",
        "homepage": ""
      },
      "release_notes": "Improved readability of cterm searches for dark backgrounds ."
    },
    {
      "url": "http://www.vim.org/scripts/download_script.php?src_id=10231",
      "filename": "maroloccio.vim",
      "script_version": "0.2.8",
      "date": "2009-03-17",
      "vim_version": "7.0",
      "author": {
        "user_id": "15725",
        "user_name": "maroloccio@yahoo.com",
        "first_name": "Marco",
        "last_name": "Ippolito",
        "email": "maroloccio at yahoo.com",
        "homepage": ""
      },
      "release_notes": "Added VimDiff colouring"
    }
  ]
}