{
  "script_id": "2575",
  "display_name": "std includes",
  "summary": "Add std:: includes to your file according to what you have used.",
  "name": "std-includes",
  "script_type": "utility",
  "description": "Add c++ std includes to your c++ file.\n\nexecute\n:StdIncludes\nto add includes.\n\nYour code should use std:: explicitly.\n\nScreen shots:\nhttp://www.railmoon.com/vim-std-includes/vim-std-includes\n\nPlease email me problems or suggestions.",
  "rating_total": "5",
  "rating_votes": "2",
  "downloads": "188",
  "install_details": "put to your vim plugin dir ( ~/.vim/plugin for nix like systems )",
  "versions": [
    {
      "url": "http://www.vim.org/scripts/download_script.php?src_id=10189",
      "filename": "std_includes.vim",
      "script_version": "0.4.1",
      "date": "2009-03-12",
      "vim_version": "7.0",
      "author": {
        "user_id": "10706",
        "user_name": "Ni",
        "first_name": "Mykola",
        "last_name": "Golubyev",
        "email": "golubev.nikolay at gmail.com",
        "homepage": "http://www.railmoon.com"
      },
      "release_notes": "Less empty lines when perform :StdIncludes without any header."
    },
    {
      "url": "http://www.vim.org/scripts/download_script.php?src_id=10141",
      "filename": "std_includes.vim",
      "script_version": "0.4",
      "date": "2009-03-08",
      "vim_version": "7.0",
      "author": {
        "user_id": "10706",
        "user_name": "Ni",
        "first_name": "Mykola",
        "last_name": "Golubyev",
        "email": "golubev.nikolay at gmail.com",
        "homepage": "http://www.railmoon.com"
      },
      "release_notes": "Initial upload"
    }
  ]
}
