{
  "script_id": "2622",
  "name": "ku-quickfix",
  "summary": "ku source: quickfix",
  "script_type": "utility",
  "description": "*ku-quickfix* is a source for |ku| to deal with |quickfix|.  You can choose\none from many files in the current quickfix list and do some action on it.\n\n\nRequirements:\n- Vim 7.2 or later\n- |ku| 0.2.0 or later (vimscript#2337)\n\nLatest version:\nhttp://github.com/kana/vim-ku-quickfix\n\nDocument in HTML format:\nhttp://kana.github.com/config/vim/ku-quickfix.html",
  "rating_total": "0",
  "rating_votes": "0",
  "downloads": "249",
  "install_details": "...",
  "versions": [
    {
      "url": "http://www.vim.org/scripts/download_script.php?src_id=10514",
      "filename": "vim-ku-quickfix-0.1.1.zip",
      "script_version": "0.1.1",
      "date": "2009-05-03",
      "vim_version": "7.0",
      "author": {
        "user_id": "13595",
        "user_name": "kana",
        "first_name": "Kana",
        "last_name": "Natsuno",
        "email": "whileimautomaton+vim at gmail.com",
        "homepage": "http://whileimautomaton.net/"
      },
      "release_notes": "- Update for ku 0.2.1.- Refactor a bit."
    },
    {
      "url": "http://www.vim.org/scripts/download_script.php?src_id=10478",
      "filename": "vim-ku-quickfix-0.1.0.zip",
      "script_version": "0.1.0",
      "date": "2009-04-28",
      "vim_version": "7.0",
      "author": {
        "user_id": "13595",
        "user_name": "kana",
        "first_name": "Kana",
        "last_name": "Natsuno",
        "email": "whileimautomaton+vim at gmail.com",
        "homepage": "http://whileimautomaton.net/"
      },
      "release_notes": "Initial upload"
    }
  ]
}