{
  "script_id": "2728",
  "display_name": "tkl.vim",
  "summary": "A syntax file to the script files used in the Tikle tool",
  "name": "tkl.vim",
  "script_type": "syntax",
  "description": "A syntax file to the script files used by the Tikle tool.\n\nMore info about Tikle at http://c2zlabs.com\n\nI've only tested this with Vim 7.1 and 7.2",
  "rating_total": "2",
  "rating_votes": "2",
  "downloads": "89",
  "install_details": "1. Copy the file to ~/.vim/syntax\n2. Add the following line to your ~/.vimrc\nau BufRead,BufNewFile *.tkl set filetype=tkl\n3. Reopen Vim or type :source ~/.vimrc to reload the configuration.",
  "versions": [
    {
      "url": "http://www.vim.org/scripts/download_script.php?src_id=11124",
      "filename": "tkl.vim",
      "script_version": "1.0",
      "date": "2009-08-03",
      "vim_version": "6.0",
      "author": {
        "user_id": "17773",
        "user_name": "enygmata",
        "first_name": "Higor",
        "last_name": "Eurípedes",
        "email": "heuripedes at gmail.com",
        "homepage": ""
      },
      "release_notes": "Initial upload"
    }
  ]
}
