{
  "script_id": "2793",
  "name": "hybridevel",
  "summary": "plugin for hybrid program",
  "script_type": "utility",
  "description": "This plugin provides lots of functions for hybrid project. Each function has \nthe shortcut and the Ex command.\n\nNow the plugin supports the following projects: c,c++,java,make,ant,\nflash, and matlab are listed in the $VIMRUNTIME/development directory. You\ncan write scripts such as python.vim to support other projects.",
  "rating_total": "0",
  "rating_votes": "0",
  "downloads": "122",
  "install_details": "",
  "versions": [
    {
      "url": "http://www.vim.org/scripts/download_script.php?src_id=12284",
      "filename": "vimhybridevel.tar.bz2",
      "script_version": "7.0",
      "date": "2010-02-03",
      "vim_version": "7.0",
      "author": {
        "user_id": "15830",
        "user_name": "WarGrey",
        "first_name": "Zhenliang",
        "last_name": "Ju",
        "email": "juzhenliang at gmail.com",
        "homepage": "http://www.wargrey.net"
      },
      "release_notes": "Its dependent plugin shellinsidevim.vim has been combined in this plugin.\nSo you can execute shell command directly with ex command :Shell,\nand the output will display in the quickfix window.\n\nBTW, if the shell command is a compiler that your vim supports, the compiler will be sourced."
    },
    {
      "url": "http://www.vim.org/scripts/download_script.php?src_id=11418",
      "filename": "Hybridevel.tar.bz2",
      "script_version": "7.0",
      "date": "2009-09-23",
      "vim_version": "7.2",
      "author": {
        "user_id": "15830",
        "user_name": "WarGrey",
        "first_name": "Zhenliang",
        "last_name": "Ju",
        "email": "juzhenliang at gmail.com",
        "homepage": "http://www.wargrey.net"
      },
      "release_notes": "Initial upload"
    }
  ]
}
