{
  "script_id": "2933",
  "name": "vim-addon-fcsh",
  "summary": "run adobe fcsh Flex compiler shell in background decreasing compilation times",
  "script_type": "utility",
  "description": "There is a Flex SDK for Linux. The complier is written in Java and has a long start time.\nTo increase speed there is the fcsh (flex compiler shell). You compile once and everything will be kept in memory. This plugin runs fcsh for you so that you can get fcsh compilation failures in your quickfix window.\n\nEnjoy!",
  "install_details": "Recommended way of installation:\nhttp://www.vim.org/scripts/script.php?script_id=2905\n\nIf you install this plugin manually you also have to get the dependencies listed in the info file manually.\n\ngit repository:\nhttp://github.com/MarcWeber/vim-addon-fcsh",
  "versions": [
    {
      "url": "http://www.vim.org/scripts/download_script.php?src_id=12206",
      "filename": "vim-addon-fcsh.zip",
      "script_version": "0.1",
      "date": "2010-01-28",
      "vim_version": "7.0",
      "author": {
        "user_id": "10341",
        "user_name": "MarcWeber",
        "first_name": "Marc",
        "last_name": "Weber",
        "email": "marco-oweber at gmx.de",
        "homepage": ""
      },
      "release_notes": "bug-fix. dependencies are found automatically now"
    }
  ]
}