{
  "script_id": "3294",
  "display_name": "grass.vim",
  "summary": "syntax file for grass",
  "name": "grass.vim",
  "script_type": "syntax",
  "description": "syntax file for grass (http://www.blue.sky.or.jp/grass/doc_ja.html).\nrepository: http://github.com/tyru/grass.vim\n\nsample:\n無限に草植えときますねｗＷＷｗｗｗｗＷＷｗｗ\n\nＹコンビネータｗｗＷＷｗｗＷｗｗｖちょｗｗＷＷＷｗＷＷＷｗｖおまｗＷＷｗＷｗｖ\n\nｗｗｗｗｖｗｖｗｗＷＷｗｖｗｗＷｗｗｖｗｗｗｗＷＷＷｗｗＷｗｗＷＷＷＷＷＷｗｗｗｗＷｗ\nｗｖｗＷＷｗＷｗｗｖｗＷＷＷｗｗｗｗｗＷｗｗｗｗｗｗＷＷｗＷＷＷｗＷＷＷＷＷＷｗＷ\nＷＷＷＷＷＷＷｗｗｗＷｗｗＷＷＷＷＷＷＷＷＷＷｗＷｗｗｗｗｗＷＷＷＷＷＷＷＷ\nＷＷＷｗｗｗｗｗＷＷＷＷＷＷＷＷＷＷＷＷｗｗｗｗＷＷＷＷＷＷＷＷＷＷＷＷＷ\nｗｗｗＷＷＷＷＷＷＷＷＷＷＷＷＷＷｗｗｗＷＷＷＷＷＷＷＷＷＷＷＷＷＷＷｗＷ\nＷＷＷＷＷＷＷＷＷＷＷＷＷＷＷＷＷｗｗｗＷｗｗｗｗｗｗｗｗｗｗｗｗｗｗＷＷＷＷ\nＷＷＷＷＷＷＷＷＷＷＷＷＷＷＷｗｗｗｗｗｗｗｗＷｗｗＷＷＷＷＷＷＷＷＷＷＷ\nＷＷＷＷＷＷＷＷＷＷＷＷＷｗｗｗｗｗｗｗｗｗｗｗｗｗｗｗｗｗｗｗｗｗｗｗｗＷｗｗｗｗ\nｗｗｗｗｗｗｗｗｗｗｗｗｗｗｗｗｗ　　　　　　　　　　　　　ｗｗｗｗｗｗｗｗＷＷｗｗｗｗｗｗｗ\nｗｗｗｗｗｗｗｗｗｗｗｗｗｗｗｗｗ　　　　　　　 　 は　　 ｗｗｗｗｗＷＷＷＷＷＷＷＷＷＷ\nＷＷＷＷＷｗＷｗｗｗＷＷＷＷ　　　　わ　　　い　　 ＷＷＷＷＷＷＷｗｗｗＷｗｗＷＷ\nＷＷＷＷＷＷＷＷＷＷｗｗｗｗ　　　　ろ　　　は　　  ｗＷｗｗｗｗｗｗｗＷＷＷＷＷＷＷ\nＷＷＷＷＷＷＷＷＷＷｗｗｗｗ　　　　す　　　い　　　ｗｗｗＷｗｗＷＷＷＷＷＷＷＷＷ\nＷＷＷＷＷＷＷＷＷｗｗｗｗｗ　　　　 わ　　　　　　　ｗｗｗｗＷｗｗＷＷＷＷＷＷＷＷ\nＷＷＷＷＷＷＷＷＷＷＷＷＷ　　　　ろ　　　　　　　ＷＷＷＷＷＷＷＷＷｗｗｗｗｗｗ\nｗｗｗｗｗＷｗｗＷＷＷＷＷＷＷ　　　 す　　　　　　　ＷＷＷＷＷＷＷＷＷｗｗｗｗｗｗ\nｗｗｗｗｗｗｗＷｗｗｗｗｗｗｗｗｗ　　　　　　　　　　　　 ｗｗｗｗｗｗＷＷＷＷＷＷＷＷＷ\nＷＷＷＷＷＷＷＷｗｗｗｗｗｗｗｗｗｗｗｗｗｗｗｗｗｗｗｗｗｗｗｗｗｗｗｗｗｗｗｗｗｗｗｗｗ\nｗｗｗｗｗｗＷｗｗｗｗｗｗｗｗｗｗｗｗｗｗＷＷｗｗｗｗｗｗｗｗｗＷＷＷｗｗＷＷＷＷｗｗｗ\nｗｗｗｗｗｗｗｗｗｗｗｗＷＷＷＷＷｗｗＷＷＷＷＷＷｗｗｗｗＷＷＷＷＷＷＷｗｗＷＷＷ\nＷＷＷＷＷｗｗｗｗＷＷＷＷＷＷＷＷＷｗｗＷＷＷＷＷＷＷＷＷＷｗｗｗｗｗｗｗｗｗ\nｗｗｗｗＷＷＷＷＷＷＷＷＷＷＷＷＷＷＷＷＷＷＷＷＷＷＷＷＷＷＷＷｗｗｗｗｗｗ\nｗｗｗｗｗＷｗｗｗＷＷｗｗｗｗｗｗｗｗｗｗｗｗｗｗｗｗｗｗＷＷＷｗｗＷＷＷＷｗｗｗｗｗｗ\nｗｗｗｗｗｗｗｗｗｗｗｗｗｗｗｗｗｗＷＷＷＷＷｗｗＷＷＷＷＷＷｗｗｗｗｗｗｗＷＷＷＷ\nＷＷＷｗｗＷＷＷＷＷＷＷＷｗｗｗｗｗｗＷＷＷＷＷＷＷＷＷｗｗＷＷＷＷＷＷＷＷ\nＷＷｗｗｗｗｗｗＷＷＷＷＷＷＷＷＷＷＷｗｗｗｗｗｗｗｗｗｗｗｗｗｗｗｗｗｗｗｗｗｗｗ",
  "install_details": "",
  "versions": [
    {
      "url": "http://www.vim.org/scripts/download_script.php?src_id=14113",
      "filename": "grass.vim",
      "script_version": "0.0.0",
      "date": "2010-10-25",
      "vim_version": "7.0",
      "author": {
        "user_id": "16618",
        "user_name": "0tyru0",
        "first_name": "tyru",
        "last_name": " ",
        "email": "tyru.exe (at) gmail.com",
        "homepage": "http://tyru.sakura.ne.jp/"
      },
      "release_notes": "Initial upload"
    }
  ]
}
