{
  "script_id": "3471",
  "display_name": "latte",
  "summary": "milk & cookies colorcheme",
  "name": "latte",
  "script_type": "color scheme",
  "description": "screenshot & credits: https://github.com/aerosol/Latte\n\nenjoy!",
  "install_details": "",
  "versions": [
    {
      "url": "http://www.vim.org/scripts/download_script.php?src_id=15117",
      "filename": "latte.vim",
      "script_version": "0.1",
      "date": "2011-02-25",
      "vim_version": "7.0",
      "author": {
        "user_id": "27293",
        "user_name": "hq1",
        "first_name": "adam",
        "last_name": "rutkowski",
        "email": "spam at mtod org",
        "homepage": ""
      },
      "release_notes": "Initial upload"
    }
  ]
}
